mm_jwt/admin.py
mm_jwt/apps.py
mm_jwt/models.py
mm_jwt/permissions.py
mm_jwt/tests.py
mm_jwt/urls.py
mm_jwt/utils.py
mm_jwt/views.py
mm_jwt/migrations/0001_initial.py
mm_jwt/migrations/0002_alter_customtoken_expire_date_and_more.py
mm_jwt/migrations/0003_customtoken_created_at_alter_customtoken_expire_date.py
mm_jwt/migrations/__init__.py
mm_jwt-0.1.2.dist-info/METADATA
mm_jwt-0.1.2.dist-info/WHEEL
mm_jwt-0.1.2.dist-info/top_level.txt
mm_jwt-0.1.2.dist-info/RECORD
