Metadata-Version: 2.1
Name: mm-jwt
Version: 0.1.2
Summary: Django rest framework token authentication
Home-page: https://github.com/mahdi2000musa/MM_JWT/
Author: Mahdi Musa Semnani, Mohammad Mahdi Nejati, Omidreza Nabavi
Author-email: mahdi.2000musa@gmail.com, mmehdi2022@gmail.com, omidrezanabavi@gmail.com
Keywords: django,rest framework,token,authentication
Requires-Dist: pytz
Requires-Dist: djangorestframework
Requires-Dist: django
